pythonjs/__init__.py
pythonjs/ds/Object.py
pythonjs/ds/__init__.py
PythonJS-0.9.0.dist-info/LICENSE
PythonJS-0.9.0.dist-info/METADATA
PythonJS-0.9.0.dist-info/WHEEL
PythonJS-0.9.0.dist-info/top_level.txt
PythonJS-0.9.0.dist-info/RECORD
